[
  {
    "id": 1,
    "marca": "Marca",
    "nome": "Peça 1",
    "preco": "X.XX",
    "parclQtd": "X",  
    "parclValor": "X.XX",
    "imagem": "/images/parts/partsOne/parts.png",
    "whatsapp": "https://wa.me/551127134750?text=Tenho%20interesse%20no%20(Produto)"
  },
  {
    "id": 2,
    "marca": "Marca",
    "nome": "Peça 2",
    "preco": "X.XX",
    "parclQtd": "X",  
    "parclValor": "X.XX",
    "imagem": "/images/parts/partsOne/parts.png",
    "whatsapp": "https://wa.me/551127134750?text=Tenho%20interesse%20no%20(Produto)"
  },
  {
    "id": 3,
    "marca": "Marca",
    "nome": "Peça 3",
    "preco": "X.XX",
    "parclQtd": "X",  
    "parclValor": "X.XX",
    "imagem": "/images/parts/partsOne/parts.png",
    "whatsapp": "https://wa.me/551127134750?text=Tenho%20interesse%20no%20(Produto)"
  },
  {
    "id": 4,
    "marca": "Marca",
    "nome": "Peça 4",
    "preco": "X.XX",
    "parclQtd": "X",  
    "parclValor": "X.XX",
    "imagem": "/images/parts/partsOne/parts.png",
    "whatsapp": "https://wa.me/551127134750?text=Tenho%20interesse%20no%20(Produto)"
  },
  {
    "id": 5,
    "marca": "Marca",
    "nome": "Peça 5",
    "preco": "X.XX",
    "parclQtd": "X",  
    "parclValor": "X.XX",
    "imagem": "/images/parts/partsOne/parts.png",
    "whatsapp": "https://wa.me/551127134750?text=Tenho%20interesse%20no%20(Produto)"
  },
  {
    "id": 6,
    "marca": "Marca",
    "nome": "Peça 6",
    "preco": "X.XX",
    "parclQtd": "X",  
    "parclValor": "X.XX",
    "imagem": "/images/parts/partsOne/parts.png",
    "whatsapp": "https://wa.me/551127134750?text=Tenho%20interesse%20no%20(Produto)"
  },
  {
    "id": 7,
    "marca": "Marca",
    "nome": "Peça 7",
    "preco": "X.XX",
    "parclQtd": "X",  
    "parclValor": "X.XX",
    "imagem": "/images/parts/partsOne/parts.png",
    "whatsapp": "https://wa.me/551127134750?text=Tenho%20interesse%20no%20(Produto)"
  },
  {
    "id": 8,
    "marca": "Marca",
    "nome": "Peça 8",
    "preco": "X.XX",
    "parclQtd": "X",  
    "parclValor": "X.XX",
    "imagem": "/images/parts/partsOne/parts.png",
    "whatsapp": "https://wa.me/551127134750?text=Tenho%20interesse%20no%20(Produto)"
  },
  {
    "id": 9,
    "marca": "Marca",
    "nome": "Peça 9",
    "preco": "X.XX",
    "parclQtd": "X",  
    "parclValor": "X.XX",
    "imagem": "/images/parts/partsOne/parts.png",
    "whatsapp": "https://wa.me/551127134750?text=Tenho%20interesse%20no%20(Produto)"
  },
  {
    "id": 10,
    "marca": "Marca",
    "nome": "Peça 10",
    "preco": "X.XX",
    "parclQtd": "X",  
    "parclValor": "X.XX",
    "imagem": "/images/parts/partsOne/parts.png",
    "whatsapp": "https://wa.me/551127134750?text=Tenho%20interesse%20no%20(Produto)"
  }
]